tastopo/__init__.py
tastopo/export.py
tastopo/image.py
tastopo/layout.py
tastopo/map.py
tastopo/types.py
tastopo/validate.py
tastopo/dimensions/__init__.py
tastopo/dimensions/paper.py
tastopo/dimensions/tilegrid.py
tastopo/mapdata/__init__.py
tastopo/mapdata/api.py
tastopo/mapdata/geometry.py
tastopo/mapdata/layer.py
tastopo/mapdata/location.py
tastopo/templates/__init__.py
tastopo/templates/default.svg
tastopo-1.2.0.data/scripts/tastopo
tastopo-1.2.0.dist-info/LICENSE.txt
tastopo-1.2.0.dist-info/METADATA
tastopo-1.2.0.dist-info/WHEEL
tastopo-1.2.0.dist-info/top_level.txt
tastopo-1.2.0.dist-info/RECORD
