Metadata-Version: 2.1
Name: tastopo
Version: 1.2.0
Summary: Generate printable topographic maps for anywhere in Tasmania
Home-page: https://github.com/jonathanholvey/tastopo
Author: Jonathan Holvey
Project-URL: Bug Reports, https://github.com/jonathanholvey/tastopo/issues
Project-URL: Source, https://github.com/jonathanholvey/tastopo/
Classifier: Development Status :: 4 - Beta
Classifier: Intended Audience :: Other Audience
Classifier: Topic :: Other/Nonlisted Topic
Classifier: License :: OSI Approved :: MIT License
Classifier: Programming Language :: Python :: 3
Requires-Python: >=3.9, <4
License-File: LICENSE.txt
Requires-Dist: docopt~=0.6
Requires-Dist: requests~=2.26
Requires-Dist: svglib~=1.1
Requires-Dist: reportlab~=3.6.13
Requires-Dist: pillow~=10.3
